CHANGES.rst
CONTRIBUTORS.rst
MANIFEST.in
README.rst
setup.cfg
setup.py
docs/LICENSE.GPL
docs/LICENSE.txt
src/s17/__init__.py
src/s17.taskmanager.egg-info/PKG-INFO
src/s17.taskmanager.egg-info/SOURCES.txt
src/s17.taskmanager.egg-info/dependency_links.txt
src/s17.taskmanager.egg-info/namespace_packages.txt
src/s17.taskmanager.egg-info/not-zip-safe
src/s17.taskmanager.egg-info/requires.txt
src/s17.taskmanager.egg-info/top_level.txt
src/s17/taskmanager/__init__.py
src/s17/taskmanager/adapters.py
src/s17/taskmanager/browser.py
src/s17/taskmanager/config.py
src/s17/taskmanager/configure.zcml
src/s17/taskmanager/content.py
src/s17/taskmanager/interfaces.py
src/s17/taskmanager/notifications.py
src/s17/taskmanager/profiles.zcml
src/s17/taskmanager/subscribers.py
src/s17/taskmanager/testing.py
src/s17/taskmanager/Extensions/Install.py
src/s17/taskmanager/locales/manual.pot
src/s17/taskmanager/locales/plone.pot
src/s17/taskmanager/locales/rebuildAll.sh
src/s17/taskmanager/locales/s17.taskmanager.pot
src/s17/taskmanager/locales/pt_BR/LC_MESSAGES/plone.mo
src/s17/taskmanager/locales/pt_BR/LC_MESSAGES/plone.po
src/s17/taskmanager/locales/pt_BR/LC_MESSAGES/s17.taskmanager.mo
src/s17/taskmanager/locales/pt_BR/LC_MESSAGES/s17.taskmanager.po
src/s17/taskmanager/profiles/default/metadata.xml
src/s17/taskmanager/profiles/default/s17.app.taskmanager-default.txt
src/s17/taskmanager/profiles/default/types.xml
src/s17/taskmanager/profiles/default/workflows.xml
src/s17/taskmanager/profiles/default/types/Task.xml
src/s17/taskmanager/profiles/default/types/TaskPanel.xml
src/s17/taskmanager/profiles/default/workflows/taskmanager_workflow/definition.xml
src/s17/taskmanager/profiles/uninstall/s17.app.taskmanager-uninstall.txt
src/s17/taskmanager/static/task_icon.png
src/s17/taskmanager/static/taskmanager.css
src/s17/taskmanager/static/taskpanel_icon.png
src/s17/taskmanager/templates/edit_response.pt
src/s17/taskmanager/templates/task_view.pt
src/s17/taskmanager/templates/taskpanel_view.pt
src/s17/taskmanager/tests/__init__.py
src/s17/taskmanager/tests/test_acceptance.py
src/s17/taskmanager/tests/test_notifications.py
src/s17/taskmanager/tests/test_setup.py
src/s17/taskmanager/tests/test_task.py
src/s17/taskmanager/tests/test_task_views.py
src/s17/taskmanager/tests/test_taskmanager.robot
